pim_sm/__init__.py
pim_sm/pim_sm_packet.py
PIM_SM-0.1.3.dist-info/LICENSE
PIM_SM-0.1.3.dist-info/METADATA
PIM_SM-0.1.3.dist-info/WHEEL
PIM_SM-0.1.3.dist-info/top_level.txt
PIM_SM-0.1.3.dist-info/RECORD
