Metadata-Version: 2.1
Name: PIM-SM
Version: 0.1.3
Summary: about sending PIM-SM protocol messages.
Author-email: SoloHand <657229783@qq.com>
License: MIT
Keywords: pim-sm,igmp,scapy,pyshark,networking
Classifier: Programming Language :: Python :: 3
Classifier: License :: OSI Approved :: MIT License
Classifier: Operating System :: OS Independent
Requires-Python: >=3.7
License-File: LICENSE
Requires-Dist: scapy >=2.4.5
Requires-Dist: pyshark >=0.4.2.12
Requires-Dist: asyncio
